[{"county_fips":"02270","county_name":null,"race_category_id":"ALL","jail_per_100k":null,"jail_pct_share":null,"population_pct_share":null,"total_confined_children":0.0,"race":"All","race_includes_hispanic":null,"race_and_ethnicity":"All","ingestion_ts":1662607150977}
,{"county_fips":"02013","county_name":"Aleutians East Borough","race_category_id":"ALL","jail_per_100k":102.0,"jail_pct_share":100.0,"population_pct_share":100.0,"total_confined_children":0.0,"race":"All","race_includes_hispanic":null,"race_and_ethnicity":"All","ingestion_ts":1662607150977}
,{"county_fips":"02016","county_name":"Aleutians West Census Area","race_category_id":"ALL","jail_per_100k":null,"jail_pct_share":null,"population_pct_share":100.0,"total_confined_children":0.0,"race":"All","race_includes_hispanic":null,"race_and_ethnicity":"All","ingestion_ts":1662607150977}
,{"county_fips":"02020","county_name":"Anchorage Municipality","race_category_id":"ALL","jail_per_100k":null,"jail_pct_share":null,"population_pct_share":100.0,"total_confined_children":0.0,"race":"All","race_includes_hispanic":null,"race_and_ethnicity":"All","ingestion_ts":1662607150977}
,{"county_fips":"02050","county_name":"Bethel Census Area","race_category_id":"ALL","jail_per_100k":44.0,"jail_pct_share":100.0,"population_pct_share":100.0,"total_confined_children":0.0,"race":"All","race_includes_hispanic":null,"race_and_ethnicity":"All","ingestion_ts":1662607150977}
,{"county_fips":"02060","county_name":"Bristol Bay Borough","race_category_id":"ALL","jail_per_100k":990.0,"jail_pct_share":100.0,"population_pct_share":100.0,"total_confined_children":0.0,"race":"All","race_includes_hispanic":null,"race_and_ethnicity":"All","ingestion_ts":1662607150977}
,{"county_fips":"02068","county_name":"Denali Borough","race_category_id":"ALL","jail_per_100k":null,"jail_pct_share":null,"population_pct_share":100.0,"total_confined_children":0.0,"race":"All","race_includes_hispanic":null,"race_and_ethnicity":"All","ingestion_ts":1662607150977}
,{"county_fips":"02070","county_name":"Dillingham Census Area","race_category_id":"ALL","jail_per_100k":63.0,"jail_pct_share":100.0,"population_pct_share":100.0,"total_confined_children":0.0,"race":"All","race_includes_hispanic":null,"race_and_ethnicity":"All","ingestion_ts":1662607150977}
,{"county_fips":"02090","county_name":"Fairbanks North Star Borough","race_category_id":"ALL","jail_per_100k":null,"jail_pct_share":null,"population_pct_share":100.0,"total_confined_children":0.0,"race":"All","race_includes_hispanic":null,"race_and_ethnicity":"All","ingestion_ts":1662607150977}
,{"county_fips":"02100","county_name":"Haines Borough","race_category_id":"ALL","jail_per_100k":313.0,"jail_pct_share":100.0,"population_pct_share":100.0,"total_confined_children":0.0,"race":"All","race_includes_hispanic":null,"race_and_ethnicity":"All","ingestion_ts":1662607150977}
,{"county_fips":"02105","county_name":"Hoonah-Angoon Census Area","race_category_id":"ALL","jail_per_100k":null,"jail_pct_share":null,"population_pct_share":100.0,"total_confined_children":0.0,"race":"All","race_includes_hispanic":null,"race_and_ethnicity":"All","ingestion_ts":1662607150977}
,{"county_fips":"02110","county_name":"Juneau City and Borough","race_category_id":"ALL","jail_per_100k":68.0,"jail_pct_share":100.0,"population_pct_share":100.0,"total_confined_children":0.0,"race":"All","race_includes_hispanic":null,"race_and_ethnicity":"All","ingestion_ts":1662607150977}
,{"county_fips":"02122","county_name":"Kenai Peninsula Borough","race_category_id":"ALL","jail_per_100k":51.0,"jail_pct_share":100.0,"population_pct_share":100.0,"total_confined_children":0.0,"race":"All","race_includes_hispanic":null,"race_and_ethnicity":"All","ingestion_ts":1662607150977}
,{"county_fips":"02130","county_name":"Ketchikan Gateway Borough","race_category_id":"ALL","jail_per_100k":null,"jail_pct_share":null,"population_pct_share":100.0,"total_confined_children":0.0,"race":"All","race_includes_hispanic":null,"race_and_ethnicity":"All","ingestion_ts":1662607150977}
,{"county_fips":"02150","county_name":"Kodiak Island Borough","race_category_id":"ALL","jail_per_100k":null,"jail_pct_share":null,"population_pct_share":100.0,"total_confined_children":0.0,"race":"All","race_includes_hispanic":null,"race_and_ethnicity":"All","ingestion_ts":1662607150977}
,{"county_fips":"02158","county_name":"Kusilvak Census Area","race_category_id":"ALL","jail_per_100k":null,"jail_pct_share":null,"population_pct_share":100.0,"total_confined_children":0.0,"race":"All","race_includes_hispanic":null,"race_and_ethnicity":"All","ingestion_ts":1662607150977}
,{"county_fips":"02164","county_name":"Lake and Peninsula Borough","race_category_id":"ALL","jail_per_100k":965.0,"jail_pct_share":100.0,"population_pct_share":100.0,"total_confined_children":0.0,"race":"All","race_includes_hispanic":null,"race_and_ethnicity":"All","ingestion_ts":1662607150977}
,{"county_fips":"02170","county_name":"Matanuska-Susitna Borough","race_category_id":"ALL","jail_per_100k":4.0,"jail_pct_share":100.0,"population_pct_share":100.0,"total_confined_children":0.0,"race":"All","race_includes_hispanic":null,"race_and_ethnicity":"All","ingestion_ts":1662607150977}
,{"county_fips":"02180","county_name":"Nome Census Area","race_category_id":"ALL","jail_per_100k":16.0,"jail_pct_share":100.0,"population_pct_share":100.0,"total_confined_children":0.0,"race":"All","race_includes_hispanic":null,"race_and_ethnicity":"All","ingestion_ts":1662607150977}
,{"county_fips":"02185","county_name":"North Slope Borough","race_category_id":"ALL","jail_per_100k":null,"jail_pct_share":null,"population_pct_share":100.0,"total_confined_children":0.0,"race":"All","race_includes_hispanic":null,"race_and_ethnicity":"All","ingestion_ts":1662607150977}
,{"county_fips":"02188","county_name":"Northwest Arctic Borough","race_category_id":"ALL","jail_per_100k":null,"jail_pct_share":null,"population_pct_share":100.0,"total_confined_children":0.0,"race":"All","race_includes_hispanic":null,"race_and_ethnicity":"All","ingestion_ts":1662607150977}
,{"county_fips":"02195","county_name":"Petersburg Borough","race_category_id":"ALL","jail_per_100k":293.0,"jail_pct_share":100.0,"population_pct_share":100.0,"total_confined_children":0.0,"race":"All","race_includes_hispanic":null,"race_and_ethnicity":"All","ingestion_ts":1662607150977}
,{"county_fips":"02198","county_name":"Prince of Wales-Hyder Census Area","race_category_id":"ALL","jail_per_100k":null,"jail_pct_share":null,"population_pct_share":100.0,"total_confined_children":0.0,"race":"All","race_includes_hispanic":null,"race_and_ethnicity":"All","ingestion_ts":1662607150977}
,{"county_fips":"02220","county_name":"Sitka City and Borough","race_category_id":"ALL","jail_per_100k":122.0,"jail_pct_share":100.0,"population_pct_share":100.0,"total_confined_children":0.0,"race":"All","race_includes_hispanic":null,"race_and_ethnicity":"All","ingestion_ts":1662607150977}
,{"county_fips":"02230","county_name":"Skagway Municipality","race_category_id":"ALL","jail_per_100k":null,"jail_pct_share":null,"population_pct_share":100.0,"total_confined_children":0.0,"race":"All","race_includes_hispanic":null,"race_and_ethnicity":"All","ingestion_ts":1662607150977}
,{"county_fips":"02240","county_name":"Southeast Fairbanks Census Area","race_category_id":"ALL","jail_per_100k":null,"jail_pct_share":null,"population_pct_share":100.0,"total_confined_children":0.0,"race":"All","race_includes_hispanic":null,"race_and_ethnicity":"All","ingestion_ts":1662607150977}
,{"county_fips":"02261","county_name":"Valdez-Cordova Census Area","race_category_id":"ALL","jail_per_100k":null,"jail_pct_share":null,"population_pct_share":100.0,"total_confined_children":0.0,"race":"All","race_includes_hispanic":null,"race_and_ethnicity":"All","ingestion_ts":1662607150977}
,{"county_fips":"02275","county_name":"Wrangell City and Borough","race_category_id":"ALL","jail_per_100k":null,"jail_pct_share":null,"population_pct_share":100.0,"total_confined_children":0.0,"race":"All","race_includes_hispanic":null,"race_and_ethnicity":"All","ingestion_ts":1662607150977}
,{"county_fips":"02282","county_name":"Yakutat City and Borough","race_category_id":"ALL","jail_per_100k":null,"jail_pct_share":null,"population_pct_share":100.0,"total_confined_children":0.0,"race":"All","race_includes_hispanic":null,"race_and_ethnicity":"All","ingestion_ts":1662607150977}
,{"county_fips":"02290","county_name":"Yukon-Koyukuk Census Area","race_category_id":"ALL","jail_per_100k":null,"jail_pct_share":null,"population_pct_share":100.0,"total_confined_children":0.0,"race":"All","race_includes_hispanic":null,"race_and_ethnicity":"All","ingestion_ts":1662607150977}
,{"county_fips":"02270","county_name":null,"race_category_id":"HISP","jail_per_100k":null,"jail_pct_share":null,"population_pct_share":null,"total_confined_children":null,"race":"Hispanic or Latino","race_includes_hispanic":true,"race_and_ethnicity":"Hispanic or Latino","ingestion_ts":1662607150977}
,{"county_fips":"02198","county_name":"Prince of Wales-Hyder Census Area","race_category_id":"HISP","jail_per_100k":null,"jail_pct_share":null,"population_pct_share":3.0,"total_confined_children":null,"race":"Hispanic or Latino","race_includes_hispanic":true,"race_and_ethnicity":"Hispanic or Latino","ingestion_ts":1662607150977}
,{"county_fips":"02185","county_name":"North Slope Borough","race_category_id":"HISP","jail_per_100k":null,"jail_pct_share":null,"population_pct_share":3.5,"total_confined_children":null,"race":"Hispanic or Latino","race_includes_hispanic":true,"race_and_ethnicity":"Hispanic or Latino","ingestion_ts":1662607150977}
,{"county_fips":"02240","county_name":"Southeast Fairbanks Census Area","race_category_id":"HISP","jail_per_100k":null,"jail_pct_share":null,"population_pct_share":6.0,"total_confined_children":null,"race":"Hispanic or Latino","race_includes_hispanic":true,"race_and_ethnicity":"Hispanic or Latino","ingestion_ts":1662607150977}
,{"county_fips":"02105","county_name":"Hoonah-Angoon Census Area","race_category_id":"HISP","jail_per_100k":null,"jail_pct_share":null,"population_pct_share":7.0,"total_confined_children":null,"race":"Hispanic or Latino","race_includes_hispanic":true,"race_and_ethnicity":"Hispanic or Latino","ingestion_ts":1662607150977}
,{"county_fips":"02220","county_name":"Sitka City and Borough","race_category_id":"HISP","jail_per_100k":248.0,"jail_pct_share":14.3,"population_pct_share":7.0,"total_confined_children":null,"race":"Hispanic or Latino","race_includes_hispanic":true,"race_and_ethnicity":"Hispanic or Latino","ingestion_ts":1662607150977}
,{"county_fips":"02090","county_name":"Fairbanks North Star Borough","race_category_id":"HISP","jail_per_100k":null,"jail_pct_share":null,"population_pct_share":8.5,"total_confined_children":null,"race":"Hispanic or Latino","race_includes_hispanic":true,"race_and_ethnicity":"Hispanic or Latino","ingestion_ts":1662607150977}
,{"county_fips":"02150","county_name":"Kodiak Island Borough","race_category_id":"HISP","jail_per_100k":null,"jail_pct_share":null,"population_pct_share":9.0,"total_confined_children":null,"race":"Hispanic or Latino","race_includes_hispanic":true,"race_and_ethnicity":"Hispanic or Latino","ingestion_ts":1662607150977}
,{"county_fips":"02275","county_name":"Wrangell City and Borough","race_category_id":"HISP","jail_per_100k":null,"jail_pct_share":null,"population_pct_share":2.9,"total_confined_children":null,"race":"Hispanic or Latino","race_includes_hispanic":true,"race_and_ethnicity":"Hispanic or Latino","ingestion_ts":1662607150977}
,{"county_fips":"02060","county_name":"Bristol Bay Borough","race_category_id":"HISP","jail_per_100k":0.0,"jail_pct_share":0.0,"population_pct_share":4.8,"total_confined_children":null,"race":"Hispanic or Latino","race_includes_hispanic":true,"race_and_ethnicity":"Hispanic or Latino","ingestion_ts":1662607150977}
,{"county_fips":"02261","county_name":"Valdez-Cordova Census Area","race_category_id":"HISP","jail_per_100k":null,"jail_pct_share":null,"population_pct_share":4.8,"total_confined_children":null,"race":"Hispanic or Latino","race_includes_hispanic":true,"race_and_ethnicity":"Hispanic or Latino","ingestion_ts":1662607150977}
,{"county_fips":"02282","county_name":"Yakutat City and Borough","race_category_id":"HISP","jail_per_100k":null,"jail_pct_share":null,"population_pct_share":4.8,"total_confined_children":null,"race":"Hispanic or Latino","race_includes_hispanic":true,"race_and_ethnicity":"Hispanic or Latino","ingestion_ts":1662607150977}
,{"county_fips":"02158","county_name":"Kusilvak Census Area","race_category_id":"HISP","jail_per_100k":null,"jail_pct_share":null,"population_pct_share":1.2,"total_confined_children":null,"race":"Hispanic or Latino","race_includes_hispanic":true,"race_and_ethnicity":"Hispanic or Latino","ingestion_ts":1662607150977}
,{"county_fips":"02070","county_name":"Dillingham Census Area","race_category_id":"HISP","jail_per_100k":0.0,"jail_pct_share":0.0,"population_pct_share":2.8,"total_confined_children":null,"race":"Hispanic or Latino","race_includes_hispanic":true,"race_and_ethnicity":"Hispanic or Latino","ingestion_ts":1662607150977}
,{"county_fips":"02130","county_name":"Ketchikan Gateway Borough","race_category_id":"HISP","jail_per_100k":null,"jail_pct_share":null,"population_pct_share":6.1,"total_confined_children":null,"race":"Hispanic or Latino","race_includes_hispanic":true,"race_and_ethnicity":"Hispanic or Latino","ingestion_ts":1662607150977}
,{"county_fips":"02110","county_name":"Juneau City and Borough","race_category_id":"HISP","jail_per_100k":0.0,"jail_pct_share":0.0,"population_pct_share":6.6,"total_confined_children":null,"race":"Hispanic or Latino","race_includes_hispanic":true,"race_and_ethnicity":"Hispanic or Latino","ingestion_ts":1662607150977}
,{"county_fips":"02195","county_name":"Petersburg Borough","race_category_id":"HISP","jail_per_100k":0.0,"jail_pct_share":0.0,"population_pct_share":6.6,"total_confined_children":null,"race":"Hispanic or Latino","race_includes_hispanic":true,"race_and_ethnicity":"Hispanic or Latino","ingestion_ts":1662607150977}
,{"county_fips":"02016","county_name":"Aleutians West Census Area","race_category_id":"HISP","jail_per_100k":null,"jail_pct_share":null,"population_pct_share":14.7,"total_confined_children":null,"race":"Hispanic or Latino","race_includes_hispanic":true,"race_and_ethnicity":"Hispanic or Latino","ingestion_ts":1662607150977}
,{"county_fips":"02013","county_name":"Aleutians East Borough","race_category_id":"HISP","jail_per_100k":0.0,"jail_pct_share":0.0,"population_pct_share":16.1,"total_confined_children":null,"race":"Hispanic or Latino","race_includes_hispanic":true,"race_and_ethnicity":"Hispanic or Latino","ingestion_ts":1662607150977}
,{"county_fips":"02164","county_name":"Lake and Peninsula Borough","race_category_id":"HISP","jail_per_100k":0.0,"jail_pct_share":0.0,"population_pct_share":2.7,"total_confined_children":null,"race":"Hispanic or Latino","race_includes_hispanic":true,"race_and_ethnicity":"Hispanic or Latino","ingestion_ts":1662607150977}
,{"county_fips":"02122","county_name":"Kenai Peninsula Borough","race_category_id":"HISP","jail_per_100k":61.0,"jail_pct_share":5.3,"population_pct_share":4.4,"total_confined_children":null,"race":"Hispanic or Latino","race_includes_hispanic":true,"race_and_ethnicity":"Hispanic or Latino","ingestion_ts":1662607150977}
,{"county_fips":"02170","county_name":"Matanuska-Susitna Borough","race_category_id":"HISP","jail_per_100k":0.0,"jail_pct_share":0.0,"population_pct_share":4.9,"total_confined_children":null,"race":"Hispanic or Latino","race_includes_hispanic":true,"race_and_ethnicity":"Hispanic or Latino","ingestion_ts":1662607150977}
,{"county_fips":"02050","county_name":"Bethel Census Area","race_category_id":"HISP","jail_per_100k":282.0,"jail_pct_share":10.0,"population_pct_share":1.6,"total_confined_children":null,"race":"Hispanic or Latino","race_includes_hispanic":true,"race_and_ethnicity":"Hispanic or Latino","ingestion_ts":1662607150977}
,{"county_fips":"02180","county_name":"Nome Census Area","race_category_id":"HISP","jail_per_100k":0.0,"jail_pct_share":0.0,"population_pct_share":1.6,"total_confined_children":null,"race":"Hispanic or Latino","race_includes_hispanic":true,"race_and_ethnicity":"Hispanic or Latino","ingestion_ts":1662607150977}
,{"county_fips":"02290","county_name":"Yukon-Koyukuk Census Area","race_category_id":"HISP","jail_per_100k":null,"jail_pct_share":null,"population_pct_share":2.1,"total_confined_children":null,"race":"Hispanic or Latino","race_includes_hispanic":true,"race_and_ethnicity":"Hispanic or Latino","ingestion_ts":1662607150977}
,{"county_fips":"02068","county_name":"Denali Borough","race_category_id":"HISP","jail_per_100k":null,"jail_pct_share":null,"population_pct_share":3.1,"total_confined_children":null,"race":"Hispanic or Latino","race_includes_hispanic":true,"race_and_ethnicity":"Hispanic or Latino","ingestion_ts":1662607150977}
,{"county_fips":"02188","county_name":"Northwest Arctic Borough","race_category_id":"HISP","jail_per_100k":null,"jail_pct_share":null,"population_pct_share":3.1,"total_confined_children":null,"race":"Hispanic or Latino","race_includes_hispanic":true,"race_and_ethnicity":"Hispanic or Latino","ingestion_ts":1662607150977}
,{"county_fips":"02100","county_name":"Haines Borough","race_category_id":"HISP","jail_per_100k":1155.0,"jail_pct_share":13.4,"population_pct_share":3.6,"total_confined_children":null,"race":"Hispanic or Latino","race_includes_hispanic":true,"race_and_ethnicity":"Hispanic or Latino","ingestion_ts":1662607150977}
,{"county_fips":"02230","county_name":"Skagway Municipality","race_category_id":"HISP","jail_per_100k":null,"jail_pct_share":null,"population_pct_share":5.7,"total_confined_children":null,"race":"Hispanic or Latino","race_includes_hispanic":true,"race_and_ethnicity":"Hispanic or Latino","ingestion_ts":1662607150977}
,{"county_fips":"02020","county_name":"Anchorage Municipality","race_category_id":"HISP","jail_per_100k":null,"jail_pct_share":null,"population_pct_share":8.9,"total_confined_children":null,"race":"Hispanic or Latino","race_includes_hispanic":true,"race_and_ethnicity":"Hispanic or Latino","ingestion_ts":1662607150977}
,{"county_fips":"02270","county_name":null,"race_category_id":"API_NH","jail_per_100k":null,"jail_pct_share":null,"population_pct_share":null,"total_confined_children":null,"race":"Asian, Native Hawaiian, and Pacific Islander","race_includes_hispanic":false,"race_and_ethnicity":"Asian, Native Hawaiian, and Pacific Islander (Non-Hispanic)","ingestion_ts":1662607150977}
,{"county_fips":"02122","county_name":"Kenai Peninsula Borough","race_category_id":"API_NH","jail_per_100k":106.0,"jail_pct_share":5.3,"population_pct_share":2.5,"total_confined_children":null,"race":"Asian, Native Hawaiian, and Pacific Islander","race_includes_hispanic":false,"race_and_ethnicity":"Asian, Native Hawaiian, and Pacific Islander (Non-Hispanic)","ingestion_ts":1662607150977}
,{"county_fips":"02068","county_name":"Denali Borough","race_category_id":"API_NH","jail_per_100k":null,"jail_pct_share":null,"population_pct_share":5.5,"total_confined_children":null,"race":"Asian, Native Hawaiian, and Pacific Islander","race_includes_hispanic":false,"race_and_ethnicity":"Asian, Native Hawaiian, and Pacific Islander (Non-Hispanic)","ingestion_ts":1662607150977}
,{"county_fips":"02020","county_name":"Anchorage Municipality","race_category_id":"API_NH","jail_per_100k":null,"jail_pct_share":null,"population_pct_share":13.5,"total_confined_children":null,"race":"Asian, Native Hawaiian, and Pacific Islander","race_includes_hispanic":false,"race_and_ethnicity":"Asian, Native Hawaiian, and Pacific Islander (Non-Hispanic)","ingestion_ts":1662607150977}
,{"county_fips":"02188","county_name":"Northwest Arctic Borough","race_category_id":"API_NH","jail_per_100k":null,"jail_pct_share":null,"population_pct_share":1.5,"total_confined_children":null,"race":"Asian, Native Hawaiian, and Pacific Islander","race_includes_hispanic":false,"race_and_ethnicity":"Asian, Native Hawaiian, and Pacific Islander (Non-Hispanic)","ingestion_ts":1662607150977}
,{"county_fips":"02105","county_name":"Hoonah-Angoon Census Area","race_category_id":"API_NH","jail_per_100k":null,"jail_pct_share":null,"population_pct_share":2.4,"total_confined_children":null,"race":"Asian, Native Hawaiian, and Pacific Islander","race_includes_hispanic":false,"race_and_ethnicity":"Asian, Native Hawaiian, and Pacific Islander (Non-Hispanic)","ingestion_ts":1662607150977}
,{"county_fips":"02230","county_name":"Skagway Municipality","race_category_id":"API_NH","jail_per_100k":null,"jail_pct_share":null,"population_pct_share":2.9,"total_confined_children":null,"race":"Asian, Native Hawaiian, and Pacific Islander","race_includes_hispanic":false,"race_and_ethnicity":"Asian, Native Hawaiian, and Pacific Islander (Non-Hispanic)","ingestion_ts":1662607150977}
,{"county_fips":"02240","county_name":"Southeast Fairbanks Census Area","race_category_id":"API_NH","jail_per_100k":null,"jail_pct_share":null,"population_pct_share":3.4,"total_confined_children":null,"race":"Asian, Native Hawaiian, and Pacific Islander","race_includes_hispanic":false,"race_and_ethnicity":"Asian, Native Hawaiian, and Pacific Islander (Non-Hispanic)","ingestion_ts":1662607150977}
,{"county_fips":"02282","county_name":"Yakutat City and Borough","race_category_id":"API_NH","jail_per_100k":null,"jail_pct_share":null,"population_pct_share":11.1,"total_confined_children":null,"race":"Asian, Native Hawaiian, and Pacific Islander","race_includes_hispanic":false,"race_and_ethnicity":"Asian, Native Hawaiian, and Pacific Islander (Non-Hispanic)","ingestion_ts":1662607150977}
,{"county_fips":"02100","county_name":"Haines Borough","race_category_id":"API_NH","jail_per_100k":0.0,"jail_pct_share":0.0,"population_pct_share":1.2,"total_confined_children":null,"race":"Asian, Native Hawaiian, and Pacific Islander","race_includes_hispanic":false,"race_and_ethnicity":"Asian, Native Hawaiian, and Pacific Islander (Non-Hispanic)","ingestion_ts":1662607150977}
,{"county_fips":"02060","county_name":"Bristol Bay Borough","race_category_id":"API_NH","jail_per_100k":0.0,"jail_pct_share":0.0,"population_pct_share":2.3,"total_confined_children":null,"race":"Asian, Native Hawaiian, and Pacific Islander","race_includes_hispanic":false,"race_and_ethnicity":"Asian, Native Hawaiian, and Pacific Islander (Non-Hispanic)","ingestion_ts":1662607150977}
,{"county_fips":"02164","county_name":"Lake and Peninsula Borough","race_category_id":"API_NH","jail_per_100k":0.0,"jail_pct_share":0.0,"population_pct_share":5.1,"total_confined_children":null,"race":"Asian, Native Hawaiian, and Pacific Islander","race_includes_hispanic":false,"race_and_ethnicity":"Asian, Native Hawaiian, and Pacific Islander (Non-Hispanic)","ingestion_ts":1662607150977}
,{"county_fips":"02195","county_name":"Petersburg Borough","race_category_id":"API_NH","jail_per_100k":0.0,"jail_pct_share":0.0,"population_pct_share":5.1,"total_confined_children":null,"race":"Asian, Native Hawaiian, and Pacific Islander","race_includes_hispanic":false,"race_and_ethnicity":"Asian, Native Hawaiian, and Pacific Islander (Non-Hispanic)","ingestion_ts":1662607150977}
,{"county_fips":"02290","county_name":"Yukon-Koyukuk Census Area","race_category_id":"API_NH","jail_per_100k":null,"jail_pct_share":null,"population_pct_share":0.7,"total_confined_children":null,"race":"Asian, Native Hawaiian, and Pacific Islander","race_includes_hispanic":false,"race_and_ethnicity":"Asian, Native Hawaiian, and Pacific Islander (Non-Hispanic)","ingestion_ts":1662607150977}
,{"county_fips":"02070","county_name":"Dillingham Census Area","race_category_id":"API_NH","jail_per_100k":0.0,"jail_pct_share":0.0,"population_pct_share":1.4,"total_confined_children":null,"race":"Asian, Native Hawaiian, and Pacific Islander","race_includes_hispanic":false,"race_and_ethnicity":"Asian, Native Hawaiian, and Pacific Islander (Non-Hispanic)","ingestion_ts":1662607150977}
,{"county_fips":"02150","county_name":"Kodiak Island Borough","race_category_id":"API_NH","jail_per_100k":null,"jail_pct_share":null,"population_pct_share":23.9,"total_confined_children":null,"race":"Asian, Native Hawaiian, and Pacific Islander","race_includes_hispanic":false,"race_and_ethnicity":"Asian, Native Hawaiian, and Pacific Islander (Non-Hispanic)","ingestion_ts":1662607150977}
,{"county_fips":"02275","county_name":"Wrangell City and Borough","race_category_id":"API_NH","jail_per_100k":null,"jail_pct_share":null,"population_pct_share":3.7,"total_confined_children":null,"race":"Asian, Native Hawaiian, and Pacific Islander","race_includes_hispanic":false,"race_and_ethnicity":"Asian, Native Hawaiian, and Pacific Islander (Non-Hispanic)","ingestion_ts":1662607150977}
,{"county_fips":"02261","county_name":"Valdez-Cordova Census Area","race_category_id":"API_NH","jail_per_100k":null,"jail_pct_share":null,"population_pct_share":5.4,"total_confined_children":null,"race":"Asian, Native Hawaiian, and Pacific Islander","race_includes_hispanic":false,"race_and_ethnicity":"Asian, Native Hawaiian, and Pacific Islander (Non-Hispanic)","ingestion_ts":1662607150977}
,{"county_fips":"02185","county_name":"North Slope Borough","race_category_id":"API_NH","jail_per_100k":null,"jail_pct_share":null,"population_pct_share":7.9,"total_confined_children":null,"race":"Asian, Native Hawaiian, and Pacific Islander","race_includes_hispanic":false,"race_and_ethnicity":"Asian, Native Hawaiian, and Pacific Islander (Non-Hispanic)","ingestion_ts":1662607150977}
,{"county_fips":"02220","county_name":"Sitka City and Borough","race_category_id":"API_NH","jail_per_100k":198.0,"jail_pct_share":14.3,"population_pct_share":8.8,"total_confined_children":null,"race":"Asian, Native Hawaiian, and Pacific Islander","race_includes_hispanic":false,"race_and_ethnicity":"Asian, Native Hawaiian, and Pacific Islander (Non-Hispanic)","ingestion_ts":1662607150977}
,{"county_fips":"02110","county_name":"Juneau City and Borough","race_category_id":"API_NH","jail_per_100k":36.0,"jail_pct_share":5.0,"population_pct_share":9.3,"total_confined_children":null,"race":"Asian, Native Hawaiian, and Pacific Islander","race_includes_hispanic":false,"race_and_ethnicity":"Asian, Native Hawaiian, and Pacific Islander (Non-Hispanic)","ingestion_ts":1662607150977}
,{"county_fips":"02158","county_name":"Kusilvak Census Area","race_category_id":"API_NH","jail_per_100k":null,"jail_pct_share":null,"population_pct_share":0.8,"total_confined_children":null,"race":"Asian, Native Hawaiian, and Pacific Islander","race_includes_hispanic":false,"race_and_ethnicity":"Asian, Native Hawaiian, and Pacific Islander (Non-Hispanic)","ingestion_ts":1662607150977}
,{"county_fips":"02013","county_name":"Aleutians East Borough","race_category_id":"API_NH","jail_per_100k":138.0,"jail_pct_share":66.7,"population_pct_share":49.1,"total_confined_children":null,"race":"Asian, Native Hawaiian, and Pacific Islander","race_includes_hispanic":false,"race_and_ethnicity":"Asian, Native Hawaiian, and Pacific Islander (Non-Hispanic)","ingestion_ts":1662607150977}
,{"county_fips":"02180","county_name":"Nome Census Area","race_category_id":"API_NH","jail_per_100k":0.0,"jail_pct_share":0.0,"population_pct_share":2.1,"total_confined_children":null,"race":"Asian, Native Hawaiian, and Pacific Islander","race_includes_hispanic":false,"race_and_ethnicity":"Asian, Native Hawaiian, and Pacific Islander (Non-Hispanic)","ingestion_ts":1662607150977}
,{"county_fips":"02170","county_name":"Matanuska-Susitna Borough","race_category_id":"API_NH","jail_per_100k":0.0,"jail_pct_share":0.0,"population_pct_share":2.6,"total_confined_children":null,"race":"Asian, Native Hawaiian, and Pacific Islander","race_includes_hispanic":false,"race_and_ethnicity":"Asian, Native Hawaiian, and Pacific Islander (Non-Hispanic)","ingestion_ts":1662607150977}
,{"county_fips":"02090","county_name":"Fairbanks North Star Borough","race_category_id":"API_NH","jail_per_100k":null,"jail_pct_share":null,"population_pct_share":4.7,"total_confined_children":null,"race":"Asian, Native Hawaiian, and Pacific Islander","race_includes_hispanic":false,"race_and_ethnicity":"Asian, Native Hawaiian, and Pacific Islander (Non-Hispanic)","ingestion_ts":1662607150977}
,{"county_fips":"02130","county_name":"Ketchikan Gateway Borough","race_category_id":"API_NH","jail_per_100k":null,"jail_pct_share":null,"population_pct_share":9.4,"total_confined_children":null,"race":"Asian, Native Hawaiian, and Pacific Islander","race_includes_hispanic":false,"race_and_ethnicity":"Asian, Native Hawaiian, and Pacific Islander (Non-Hispanic)","ingestion_ts":1662607150977}
,{"county_fips":"02016","county_name":"Aleutians West Census Area","race_category_id":"API_NH","jail_per_100k":null,"jail_pct_share":null,"population_pct_share":43.6,"total_confined_children":null,"race":"Asian, Native Hawaiian, and Pacific Islander","race_includes_hispanic":false,"race_and_ethnicity":"Asian, Native Hawaiian, and Pacific Islander (Non-Hispanic)","ingestion_ts":1662607150977}
,{"county_fips":"02050","county_name":"Bethel Census Area","race_category_id":"API_NH","jail_per_100k":0.0,"jail_pct_share":0.0,"population_pct_share":1.3,"total_confined_children":null,"race":"Asian, Native Hawaiian, and Pacific Islander","race_includes_hispanic":false,"race_and_ethnicity":"Asian, Native Hawaiian, and Pacific Islander (Non-Hispanic)","ingestion_ts":1662607150977}
,{"county_fips":"02198","county_name":"Prince of Wales-Hyder Census Area","race_category_id":"API_NH","jail_per_100k":null,"jail_pct_share":null,"population_pct_share":1.8,"total_confined_children":null,"race":"Asian, Native Hawaiian, and Pacific Islander","race_includes_hispanic":false,"race_and_ethnicity":"Asian, Native Hawaiian, and Pacific Islander (Non-Hispanic)","ingestion_ts":1662607150977}
,{"county_fips":"02270","county_name":null,"race_category_id":"AIAN_NH","jail_per_100k":null,"jail_pct_share":null,"population_pct_share":null,"total_confined_children":null,"race":"American Indian and Alaska Native","race_includes_hispanic":false,"race_and_ethnicity":"American Indian and Alaska Native (Non-Hispanic)","ingestion_ts":1662607150977}
,{"county_fips":"02068","county_name":"Denali Borough","race_category_id":"AIAN_NH","jail_per_100k":null,"jail_pct_share":null,"population_pct_share":5.0,"total_confined_children":null,"race":"American Indian and Alaska Native","race_includes_hispanic":false,"race_and_ethnicity":"American Indian and Alaska Native (Non-Hispanic)","ingestion_ts":1662607150977}
,{"county_fips":"02170","county_name":"Matanuska-Susitna Borough","race_category_id":"AIAN_NH","jail_per_100k":53.0,"jail_pct_share":100.0,"population_pct_share":8.0,"total_confined_children":null,"race":"American Indian and Alaska Native","race_includes_hispanic":false,"race_and_ethnicity":"American Indian and Alaska Native (Non-Hispanic)","ingestion_ts":1662607150977}
,{"county_fips":"02020","county_name":"Anchorage Municipality","race_category_id":"AIAN_NH","jail_per_100k":null,"jail_pct_share":null,"population_pct_share":9.0,"total_confined_children":null,"race":"American Indian and Alaska Native","race_includes_hispanic":false,"race_and_ethnicity":"American Indian and Alaska Native (Non-Hispanic)","ingestion_ts":1662607150977}
,{"county_fips":"02105","county_name":"Hoonah-Angoon Census Area","race_category_id":"AIAN_NH","jail_per_100k":null,"jail_pct_share":null,"population_pct_share":40.5,"total_confined_children":null,"race":"American Indian and Alaska Native","race_includes_hispanic":false,"race_and_ethnicity":"American Indian and Alaska Native (Non-Hispanic)","ingestion_ts":1662607150977}
,{"county_fips":"02282","county_name":"Yakutat City and Borough","race_category_id":"AIAN_NH","jail_per_100k":null,"jail_pct_share":null,"population_pct_share":43.5,"total_confined_children":null,"race":"American Indian and Alaska Native","race_includes_hispanic":false,"race_and_ethnicity":"American Indian and Alaska Native (Non-Hispanic)","ingestion_ts":1662607150977}
,{"county_fips":"02016","county_name":"Aleutians West Census Area","race_category_id":"AIAN_NH","jail_per_100k":null,"jail_pct_share":null,"population_pct_share":9.1,"total_confined_children":null,"race":"American Indian and Alaska Native","race_includes_hispanic":false,"race_and_ethnicity":"American Indian and Alaska Native (Non-Hispanic)","ingestion_ts":1662607150977}
,{"county_fips":"02122","county_name":"Kenai Peninsula Borough","race_category_id":"AIAN_NH","jail_per_100k":167.0,"jail_pct_share":31.6,"population_pct_share":9.6,"total_confined_children":null,"race":"American Indian and Alaska Native","race_includes_hispanic":false,"race_and_ethnicity":"American Indian and Alaska Native (Non-Hispanic)","ingestion_ts":1662607150977}
,{"county_fips":"02110","county_name":"Juneau City and Borough","race_category_id":"AIAN_NH","jail_per_100k":310.0,"jail_pct_share":60.0,"population_pct_share":13.1,"total_confined_children":null,"race":"American Indian and Alaska Native","race_includes_hispanic":false,"race_and_ethnicity":"American Indian and Alaska Native (Non-Hispanic)","ingestion_ts":1662607150977}
,{"county_fips":"02240","county_name":"Southeast Fairbanks Census Area","race_category_id":"AIAN_NH","jail_per_100k":null,"jail_pct_share":null,"population_pct_share":13.1,"total_confined_children":null,"race":"American Indian and Alaska Native","race_includes_hispanic":false,"race_and_ethnicity":"American Indian and Alaska Native (Non-Hispanic)","ingestion_ts":1662607150977}
,{"county_fips":"02158","county_name":"Kusilvak Census Area","race_category_id":"AIAN_NH","jail_per_100k":null,"jail_pct_share":null,"population_pct_share":92.8,"total_confined_children":null,"race":"American Indian and Alaska Native","race_includes_hispanic":false,"race_and_ethnicity":"American Indian and Alaska Native (Non-Hispanic)","ingestion_ts":1662607150977}
,{"county_fips":"02185","county_name":"North Slope Borough","race_category_id":"AIAN_NH","jail_per_100k":null,"jail_pct_share":null,"population_pct_share":45.4,"total_confined_children":null,"race":"American Indian and Alaska Native","race_includes_hispanic":false,"race_and_ethnicity":"American Indian and Alaska Native (Non-Hispanic)","ingestion_ts":1662607150977}
,{"county_fips":"02100","county_name":"Haines Borough","race_category_id":"AIAN_NH","jail_per_100k":344.0,"jail_pct_share":13.4,"population_pct_share":12.2,"total_confined_children":null,"race":"American Indian and Alaska Native","race_includes_hispanic":false,"race_and_ethnicity":"American Indian and Alaska Native (Non-Hispanic)","ingestion_ts":1662607150977}
,{"county_fips":"02261","county_name":"Valdez-Cordova Census Area","race_category_id":"AIAN_NH","jail_per_100k":null,"jail_pct_share":null,"population_pct_share":14.7,"total_confined_children":null,"race":"American Indian and Alaska Native","race_includes_hispanic":false,"race_and_ethnicity":"American Indian and Alaska Native (Non-Hispanic)","ingestion_ts":1662607150977}
,{"county_fips":"02275","county_name":"Wrangell City and Borough","race_category_id":"AIAN_NH","jail_per_100k":null,"jail_pct_share":null,"population_pct_share":19.4,"total_confined_children":null,"race":"American Indian and Alaska Native","race_includes_hispanic":false,"race_and_ethnicity":"American Indian and Alaska Native (Non-Hispanic)","ingestion_ts":1662607150977}
,{"county_fips":"02180","county_name":"Nome Census Area","race_category_id":"AIAN_NH","jail_per_100k":63.0,"jail_pct_share":300.0,"population_pct_share":75.6,"total_confined_children":null,"race":"American Indian and Alaska Native","race_includes_hispanic":false,"race_and_ethnicity":"American Indian and Alaska Native (Non-Hispanic)","ingestion_ts":1662607150977}
,{"county_fips":"02220","county_name":"Sitka City and Borough","race_category_id":"AIAN_NH","jail_per_100k":153.0,"jail_pct_share":21.4,"population_pct_share":17.1,"total_confined_children":null,"race":"American Indian and Alaska Native","race_includes_hispanic":false,"race_and_ethnicity":"American Indian and Alaska Native (Non-Hispanic)","ingestion_ts":1662607150977}
,{"county_fips":"02090","county_name":"Fairbanks North Star Borough","race_category_id":"AIAN_NH","jail_per_100k":null,"jail_pct_share":null,"population_pct_share":8.3,"total_confined_children":null,"race":"American Indian and Alaska Native","race_includes_hispanic":false,"race_and_ethnicity":"American Indian and Alaska Native (Non-Hispanic)","ingestion_ts":1662607150977}
,{"county_fips":"02195","county_name":"Petersburg Borough","race_category_id":"AIAN_NH","jail_per_100k":0.0,"jail_pct_share":0.0,"population_pct_share":11.8,"total_confined_children":null,"race":"American Indian and Alaska Native","race_includes_hispanic":false,"race_and_ethnicity":"American Indian and Alaska Native (Non-Hispanic)","ingestion_ts":1662607150977}
,{"county_fips":"02013","county_name":"Aleutians East Borough","race_category_id":"AIAN_NH","jail_per_100k":0.0,"jail_pct_share":0.0,"population_pct_share":13.8,"total_confined_children":null,"race":"American Indian and Alaska Native","race_includes_hispanic":false,"race_and_ethnicity":"American Indian and Alaska Native (Non-Hispanic)","ingestion_ts":1662607150977}
,{"county_fips":"02130","county_name":"Ketchikan Gateway Borough","race_category_id":"AIAN_NH","jail_per_100k":null,"jail_pct_share":null,"population_pct_share":15.8,"total_confined_children":null,"race":"American Indian and Alaska Native","race_includes_hispanic":false,"race_and_ethnicity":"American Indian and Alaska Native (Non-Hispanic)","ingestion_ts":1662607150977}
,{"county_fips":"02164","county_name":"Lake and Peninsula Borough","race_category_id":"AIAN_NH","jail_per_100k":305.0,"jail_pct_share":20.0,"population_pct_share":63.2,"total_confined_children":null,"race":"American Indian and Alaska Native","race_includes_hispanic":false,"race_and_ethnicity":"American Indian and Alaska Native (Non-Hispanic)","ingestion_ts":1662607150977}
,{"county_fips":"02070","county_name":"Dillingham Census Area","race_category_id":"AIAN_NH","jail_per_100k":0.0,"jail_pct_share":0.0,"population_pct_share":74.4,"total_confined_children":null,"race":"American Indian and Alaska Native","race_includes_hispanic":false,"race_and_ethnicity":"American Indian and Alaska Native (Non-Hispanic)","ingestion_ts":1662607150977}
,{"county_fips":"02050","county_name":"Bethel Census Area","race_category_id":"AIAN_NH","jail_per_100k":42.0,"jail_pct_share":80.0,"population_pct_share":83.9,"total_confined_children":null,"race":"American Indian and Alaska Native","race_includes_hispanic":false,"race_and_ethnicity":"American Indian and Alaska Native (Non-Hispanic)","ingestion_ts":1662607150977}
,{"county_fips":"02198","county_name":"Prince of Wales-Hyder Census Area","race_category_id":"AIAN_NH","jail_per_100k":null,"jail_pct_share":null,"population_pct_share":44.1,"total_confined_children":null,"race":"American Indian and Alaska Native","race_includes_hispanic":false,"race_and_ethnicity":"American Indian and Alaska Native (Non-Hispanic)","ingestion_ts":1662607150977}
,{"county_fips":"02290","county_name":"Yukon-Koyukuk Census Area","race_category_id":"AIAN_NH","jail_per_100k":null,"jail_pct_share":null,"population_pct_share":72.7,"total_confined_children":null,"race":"American Indian and Alaska Native","race_includes_hispanic":false,"race_and_ethnicity":"American Indian and Alaska Native (Non-Hispanic)","ingestion_ts":1662607150977}
,{"county_fips":"02188","county_name":"Northwest Arctic Borough","race_category_id":"AIAN_NH","jail_per_100k":null,"jail_pct_share":null,"population_pct_share":78.2,"total_confined_children":null,"race":"American Indian and Alaska Native","race_includes_hispanic":false,"race_and_ethnicity":"American Indian and Alaska Native (Non-Hispanic)","ingestion_ts":1662607150977}
,{"county_fips":"02230","county_name":"Skagway Municipality","race_category_id":"AIAN_NH","jail_per_100k":null,"jail_pct_share":null,"population_pct_share":6.2,"total_confined_children":null,"race":"American Indian and Alaska Native","race_includes_hispanic":false,"race_and_ethnicity":"American Indian and Alaska Native (Non-Hispanic)","ingestion_ts":1662607150977}
,{"county_fips":"02150","county_name":"Kodiak Island Borough","race_category_id":"AIAN_NH","jail_per_100k":null,"jail_pct_share":null,"population_pct_share":13.4,"total_confined_children":null,"race":"American Indian and Alaska Native","race_includes_hispanic":false,"race_and_ethnicity":"American Indian and Alaska Native (Non-Hispanic)","ingestion_ts":1662607150977}
,{"county_fips":"02060","county_name":"Bristol Bay Borough","race_category_id":"AIAN_NH","jail_per_100k":2083.0,"jail_pct_share":83.3,"population_pct_share":39.6,"total_confined_children":null,"race":"American Indian and Alaska Native","race_includes_hispanic":false,"race_and_ethnicity":"American Indian and Alaska Native (Non-Hispanic)","ingestion_ts":1662607150977}
,{"county_fips":"02270","county_name":null,"race_category_id":"BLACK_NH","jail_per_100k":null,"jail_pct_share":null,"population_pct_share":null,"total_confined_children":null,"race":"Black or African American","race_includes_hispanic":false,"race_and_ethnicity":"Black or African American (Non-Hispanic)","ingestion_ts":1662607150977}
,{"county_fips":"02185","county_name":"North Slope Borough","race_category_id":"BLACK_NH","jail_per_100k":null,"jail_pct_share":null,"population_pct_share":2.0,"total_confined_children":null,"race":"Black or African American","race_includes_hispanic":false,"race_and_ethnicity":"Black or African American (Non-Hispanic)","ingestion_ts":1662607150977}
,{"county_fips":"02090","county_name":"Fairbanks North Star Borough","race_category_id":"BLACK_NH","jail_per_100k":null,"jail_pct_share":null,"population_pct_share":6.0,"total_confined_children":null,"race":"Black or African American","race_includes_hispanic":false,"race_and_ethnicity":"Black or African American (Non-Hispanic)","ingestion_ts":1662607150977}
,{"county_fips":"02158","county_name":"Kusilvak Census Area","race_category_id":"BLACK_NH","jail_per_100k":null,"jail_pct_share":null,"population_pct_share":0.5,"total_confined_children":null,"race":"Black or African American","race_includes_hispanic":false,"race_and_ethnicity":"Black or African American (Non-Hispanic)","ingestion_ts":1662607150977}
,{"county_fips":"02122","county_name":"Kenai Peninsula Borough","race_category_id":"BLACK_NH","jail_per_100k":353.0,"jail_pct_share":7.2,"population_pct_share":1.0,"total_confined_children":null,"race":"Black or African American","race_includes_hispanic":false,"race_and_ethnicity":"Black or African American (Non-Hispanic)","ingestion_ts":1662607150977}
,{"county_fips":"02100","county_name":"Haines Borough","race_category_id":"BLACK_NH","jail_per_100k":4167.0,"jail_pct_share":20.0,"population_pct_share":1.5,"total_confined_children":null,"race":"Black or African American","race_includes_hispanic":false,"race_and_ethnicity":"Black or African American (Non-Hispanic)","ingestion_ts":1662607150977}
,{"county_fips":"02150","county_name":"Kodiak Island Borough","race_category_id":"BLACK_NH","jail_per_100k":null,"jail_pct_share":null,"population_pct_share":1.5,"total_confined_children":null,"race":"Black or African American","race_includes_hispanic":false,"race_and_ethnicity":"Black or African American (Non-Hispanic)","ingestion_ts":1662607150977}
,{"county_fips":"02220","county_name":"Sitka City and Borough","race_category_id":"BLACK_NH","jail_per_100k":0.0,"jail_pct_share":0.0,"population_pct_share":1.5,"total_confined_children":null,"race":"Black or African American","race_includes_hispanic":false,"race_and_ethnicity":"Black or African American (Non-Hispanic)","ingestion_ts":1662607150977}
,{"county_fips":"02164","county_name":"Lake and Peninsula Borough","race_category_id":"BLACK_NH","jail_per_100k":0.0,"jail_pct_share":0.0,"population_pct_share":2.4,"total_confined_children":null,"race":"Black or African American","race_includes_hispanic":false,"race_and_ethnicity":"Black or African American (Non-Hispanic)","ingestion_ts":1662607150977}
,{"county_fips":"02282","county_name":"Yakutat City and Borough","race_category_id":"BLACK_NH","jail_per_100k":null,"jail_pct_share":null,"population_pct_share":5.3,"total_confined_children":null,"race":"Black or African American","race_includes_hispanic":false,"race_and_ethnicity":"Black or African American (Non-Hispanic)","ingestion_ts":1662607150977}
,{"county_fips":"02020","county_name":"Anchorage Municipality","race_category_id":"BLACK_NH","jail_per_100k":null,"jail_pct_share":null,"population_pct_share":6.8,"total_confined_children":null,"race":"Black or African American","race_includes_hispanic":false,"race_and_ethnicity":"Black or African American (Non-Hispanic)","ingestion_ts":1662607150977}
,{"county_fips":"02070","county_name":"Dillingham Census Area","race_category_id":"BLACK_NH","jail_per_100k":0.0,"jail_pct_share":0.0,"population_pct_share":1.2,"total_confined_children":null,"race":"Black or African American","race_includes_hispanic":false,"race_and_ethnicity":"Black or African American (Non-Hispanic)","ingestion_ts":1662607150977}
,{"county_fips":"02180","county_name":"Nome Census Area","race_category_id":"BLACK_NH","jail_per_100k":0.0,"jail_pct_share":0.0,"population_pct_share":1.2,"total_confined_children":null,"race":"Black or African American","race_includes_hispanic":false,"race_and_ethnicity":"Black or African American (Non-Hispanic)","ingestion_ts":1662607150977}
,{"county_fips":"02198","county_name":"Prince of Wales-Hyder Census Area","race_category_id":"BLACK_NH","jail_per_100k":null,"jail_pct_share":null,"population_pct_share":1.2,"total_confined_children":null,"race":"Black or African American","race_includes_hispanic":false,"race_and_ethnicity":"Black or African American (Non-Hispanic)","ingestion_ts":1662607150977}
,{"county_fips":"02230","county_name":"Skagway Municipality","race_category_id":"BLACK_NH","jail_per_100k":null,"jail_pct_share":null,"population_pct_share":1.2,"total_confined_children":null,"race":"Black or African American","race_includes_hispanic":false,"race_and_ethnicity":"Black or African American (Non-Hispanic)","ingestion_ts":1662607150977}
,{"county_fips":"02110","county_name":"Juneau City and Borough","race_category_id":"BLACK_NH","jail_per_100k":0.0,"jail_pct_share":0.0,"population_pct_share":1.7,"total_confined_children":null,"race":"Black or African American","race_includes_hispanic":false,"race_and_ethnicity":"Black or African American (Non-Hispanic)","ingestion_ts":1662607150977}
,{"county_fips":"02170","county_name":"Matanuska-Susitna Borough","race_category_id":"BLACK_NH","jail_per_100k":0.0,"jail_pct_share":0.0,"population_pct_share":1.7,"total_confined_children":null,"race":"Black or African American","race_includes_hispanic":false,"race_and_ethnicity":"Black or African American (Non-Hispanic)","ingestion_ts":1662607150977}
,{"county_fips":"02105","county_name":"Hoonah-Angoon Census Area","race_category_id":"BLACK_NH","jail_per_100k":null,"jail_pct_share":null,"population_pct_share":3.8,"total_confined_children":null,"race":"Black or African American","race_includes_hispanic":false,"race_and_ethnicity":"Black or African American (Non-Hispanic)","ingestion_ts":1662607150977}
,{"county_fips":"02016","county_name":"Aleutians West Census Area","race_category_id":"BLACK_NH","jail_per_100k":null,"jail_pct_share":null,"population_pct_share":7.6,"total_confined_children":null,"race":"Black or African American","race_includes_hispanic":false,"race_and_ethnicity":"Black or African American (Non-Hispanic)","ingestion_ts":1662607150977}
,{"county_fips":"02188","county_name":"Northwest Arctic Borough","race_category_id":"BLACK_NH","jail_per_100k":null,"jail_pct_share":null,"population_pct_share":1.4,"total_confined_children":null,"race":"Black or African American","race_includes_hispanic":false,"race_and_ethnicity":"Black or African American (Non-Hispanic)","ingestion_ts":1662607150977}
,{"county_fips":"02240","county_name":"Southeast Fairbanks Census Area","race_category_id":"BLACK_NH","jail_per_100k":null,"jail_pct_share":null,"population_pct_share":1.9,"total_confined_children":null,"race":"Black or African American","race_includes_hispanic":false,"race_and_ethnicity":"Black or African American (Non-Hispanic)","ingestion_ts":1662607150977}
,{"county_fips":"02068","county_name":"Denali Borough","race_category_id":"BLACK_NH","jail_per_100k":null,"jail_pct_share":null,"population_pct_share":3.2,"total_confined_children":null,"race":"Black or African American","race_includes_hispanic":false,"race_and_ethnicity":"Black or African American (Non-Hispanic)","ingestion_ts":1662607150977}
,{"county_fips":"02013","county_name":"Aleutians East Borough","race_category_id":"BLACK_NH","jail_per_100k":275.0,"jail_pct_share":33.3,"population_pct_share":12.3,"total_confined_children":null,"race":"Black or African American","race_includes_hispanic":false,"race_and_ethnicity":"Black or African American (Non-Hispanic)","ingestion_ts":1662607150977}
,{"county_fips":"02050","county_name":"Bethel Census Area","race_category_id":"BLACK_NH","jail_per_100k":0.0,"jail_pct_share":0.0,"population_pct_share":1.1,"total_confined_children":null,"race":"Black or African American","race_includes_hispanic":false,"race_and_ethnicity":"Black or African American (Non-Hispanic)","ingestion_ts":1662607150977}
,{"county_fips":"02290","county_name":"Yukon-Koyukuk Census Area","race_category_id":"BLACK_NH","jail_per_100k":null,"jail_pct_share":null,"population_pct_share":1.1,"total_confined_children":null,"race":"Black or African American","race_includes_hispanic":false,"race_and_ethnicity":"Black or African American (Non-Hispanic)","ingestion_ts":1662607150977}
,{"county_fips":"02060","county_name":"Bristol Bay Borough","race_category_id":"BLACK_NH","jail_per_100k":0.0,"jail_pct_share":0.0,"population_pct_share":2.6,"total_confined_children":null,"race":"Black or African American","race_includes_hispanic":false,"race_and_ethnicity":"Black or African American (Non-Hispanic)","ingestion_ts":1662607150977}
,{"county_fips":"02195","county_name":"Petersburg Borough","race_category_id":"BLACK_NH","jail_per_100k":0.0,"jail_pct_share":0.0,"population_pct_share":2.6,"total_confined_children":null,"race":"Black or African American","race_includes_hispanic":false,"race_and_ethnicity":"Black or African American (Non-Hispanic)","ingestion_ts":1662607150977}
,{"county_fips":"02130","county_name":"Ketchikan Gateway Borough","race_category_id":"BLACK_NH","jail_per_100k":null,"jail_pct_share":null,"population_pct_share":1.3,"total_confined_children":null,"race":"Black or African American","race_includes_hispanic":false,"race_and_ethnicity":"Black or African American (Non-Hispanic)","ingestion_ts":1662607150977}
,{"county_fips":"02261","county_name":"Valdez-Cordova Census Area","race_category_id":"BLACK_NH","jail_per_100k":null,"jail_pct_share":null,"population_pct_share":1.3,"total_confined_children":null,"race":"Black or African American","race_includes_hispanic":false,"race_and_ethnicity":"Black or African American (Non-Hispanic)","ingestion_ts":1662607150977}
,{"county_fips":"02275","county_name":"Wrangell City and Borough","race_category_id":"BLACK_NH","jail_per_100k":null,"jail_pct_share":null,"population_pct_share":1.3,"total_confined_children":null,"race":"Black or African American","race_includes_hispanic":false,"race_and_ethnicity":"Black or African American (Non-Hispanic)","ingestion_ts":1662607150977}
,{"county_fips":"02270","county_name":null,"race_category_id":"WHITE_NH","jail_per_100k":null,"jail_pct_share":null,"population_pct_share":null,"total_confined_children":null,"race":"White","race_includes_hispanic":false,"race_and_ethnicity":"White (Non-Hispanic)","ingestion_ts":1662607150977}
,{"county_fips":"02100","county_name":"Haines Borough","race_category_id":"WHITE_NH","jail_per_100k":460.0,"jail_pct_share":120.0,"population_pct_share":81.5,"total_confined_children":null,"race":"White","race_includes_hispanic":false,"race_and_ethnicity":"White (Non-Hispanic)","ingestion_ts":1662607150977}
,{"county_fips":"02180","county_name":"Nome Census Area","race_category_id":"WHITE_NH","jail_per_100k":246.0,"jail_pct_share":300.0,"population_pct_share":19.5,"total_confined_children":null,"race":"White","race_includes_hispanic":false,"race_and_ethnicity":"White (Non-Hispanic)","ingestion_ts":1662607150977}
,{"county_fips":"02164","county_name":"Lake and Peninsula Borough","race_category_id":"WHITE_NH","jail_per_100k":105.0,"jail_pct_share":2.9,"population_pct_share":26.5,"total_confined_children":null,"race":"White","race_includes_hispanic":false,"race_and_ethnicity":"White (Non-Hispanic)","ingestion_ts":1662607150977}
,{"county_fips":"02050","county_name":"Bethel Census Area","race_category_id":"WHITE_NH","jail_per_100k":165.0,"jail_pct_share":45.0,"population_pct_share":12.1,"total_confined_children":null,"race":"White","race_includes_hispanic":false,"race_and_ethnicity":"White (Non-Hispanic)","ingestion_ts":1662607150977}
,{"county_fips":"02070","county_name":"Dillingham Census Area","race_category_id":"WHITE_NH","jail_per_100k":156.0,"jail_pct_share":50.0,"population_pct_share":20.2,"total_confined_children":null,"race":"White","race_includes_hispanic":false,"race_and_ethnicity":"White (Non-Hispanic)","ingestion_ts":1662607150977}
,{"county_fips":"02110","county_name":"Juneau City and Borough","race_category_id":"WHITE_NH","jail_per_100k":5.0,"jail_pct_share":5.0,"population_pct_share":69.3,"total_confined_children":null,"race":"White","race_includes_hispanic":false,"race_and_ethnicity":"White (Non-Hispanic)","ingestion_ts":1662607150977}
,{"county_fips":"02282","county_name":"Yakutat City and Borough","race_category_id":"WHITE_NH","jail_per_100k":null,"jail_pct_share":null,"population_pct_share":35.4,"total_confined_children":null,"race":"White","race_includes_hispanic":false,"race_and_ethnicity":"White (Non-Hispanic)","ingestion_ts":1662607150977}
,{"county_fips":"02170","county_name":"Matanuska-Susitna Borough","race_category_id":"WHITE_NH","jail_per_100k":9.0,"jail_pct_share":166.7,"population_pct_share":82.8,"total_confined_children":null,"race":"White","race_includes_hispanic":false,"race_and_ethnicity":"White (Non-Hispanic)","ingestion_ts":1662607150977}
,{"county_fips":"02198","county_name":"Prince of Wales-Hyder Census Area","race_category_id":"WHITE_NH","jail_per_100k":null,"jail_pct_share":null,"population_pct_share":49.9,"total_confined_children":null,"race":"White","race_includes_hispanic":false,"race_and_ethnicity":"White (Non-Hispanic)","ingestion_ts":1662607150977}
,{"county_fips":"02105","county_name":"Hoonah-Angoon Census Area","race_category_id":"WHITE_NH","jail_per_100k":null,"jail_pct_share":null,"population_pct_share":46.3,"total_confined_children":null,"race":"White","race_includes_hispanic":false,"race_and_ethnicity":"White (Non-Hispanic)","ingestion_ts":1662607150977}
,{"county_fips":"02150","county_name":"Kodiak Island Borough","race_category_id":"WHITE_NH","jail_per_100k":null,"jail_pct_share":null,"population_pct_share":52.3,"total_confined_children":null,"race":"White","race_includes_hispanic":false,"race_and_ethnicity":"White (Non-Hispanic)","ingestion_ts":1662607150977}
,{"county_fips":"02275","county_name":"Wrangell City and Borough","race_category_id":"WHITE_NH","jail_per_100k":null,"jail_pct_share":null,"population_pct_share":72.6,"total_confined_children":null,"race":"White","race_includes_hispanic":false,"race_and_ethnicity":"White (Non-Hispanic)","ingestion_ts":1662607150977}
,{"county_fips":"02013","county_name":"Aleutians East Borough","race_category_id":"WHITE_NH","jail_per_100k":1163.0,"jail_pct_share":100.0,"population_pct_share":8.7,"total_confined_children":null,"race":"White","race_includes_hispanic":false,"race_and_ethnicity":"White (Non-Hispanic)","ingestion_ts":1662607150977}
,{"county_fips":"02188","county_name":"Northwest Arctic Borough","race_category_id":"WHITE_NH","jail_per_100k":null,"jail_pct_share":null,"population_pct_share":15.7,"total_confined_children":null,"race":"White","race_includes_hispanic":false,"race_and_ethnicity":"White (Non-Hispanic)","ingestion_ts":1662607150977}
,{"county_fips":"02290","county_name":"Yukon-Koyukuk Census Area","race_category_id":"WHITE_NH","jail_per_100k":null,"jail_pct_share":null,"population_pct_share":23.4,"total_confined_children":null,"race":"White","race_includes_hispanic":false,"race_and_ethnicity":"White (Non-Hispanic)","ingestion_ts":1662607150977}
,{"county_fips":"02220","county_name":"Sitka City and Borough","race_category_id":"WHITE_NH","jail_per_100k":106.0,"jail_pct_share":57.1,"population_pct_share":65.6,"total_confined_children":null,"race":"White","race_includes_hispanic":false,"race_and_ethnicity":"White (Non-Hispanic)","ingestion_ts":1662607150977}
,{"county_fips":"02240","county_name":"Southeast Fairbanks Census Area","race_category_id":"WHITE_NH","jail_per_100k":null,"jail_pct_share":null,"population_pct_share":75.6,"total_confined_children":null,"race":"White","race_includes_hispanic":false,"race_and_ethnicity":"White (Non-Hispanic)","ingestion_ts":1662607150977}
,{"county_fips":"02016","county_name":"Aleutians West Census Area","race_category_id":"WHITE_NH","jail_per_100k":null,"jail_pct_share":null,"population_pct_share":25.1,"total_confined_children":null,"race":"White","race_includes_hispanic":false,"race_and_ethnicity":"White (Non-Hispanic)","ingestion_ts":1662607150977}
,{"county_fips":"02090","county_name":"Fairbanks North Star Borough","race_category_id":"WHITE_NH","jail_per_100k":null,"jail_pct_share":null,"population_pct_share":72.4,"total_confined_children":null,"race":"White","race_includes_hispanic":false,"race_and_ethnicity":"White (Non-Hispanic)","ingestion_ts":1662607150977}
,{"county_fips":"02060","county_name":"Bristol Bay Borough","race_category_id":"WHITE_NH","jail_per_100k":326.0,"jail_pct_share":16.7,"population_pct_share":50.7,"total_confined_children":null,"race":"White","race_includes_hispanic":false,"race_and_ethnicity":"White (Non-Hispanic)","ingestion_ts":1662607150977}
,{"county_fips":"02195","county_name":"Petersburg Borough","race_category_id":"WHITE_NH","jail_per_100k":265.0,"jail_pct_share":66.7,"population_pct_share":73.9,"total_confined_children":null,"race":"White","race_includes_hispanic":false,"race_and_ethnicity":"White (Non-Hispanic)","ingestion_ts":1662607150977}
,{"county_fips":"02261","county_name":"Valdez-Cordova Census Area","race_category_id":"WHITE_NH","jail_per_100k":null,"jail_pct_share":null,"population_pct_share":73.9,"total_confined_children":null,"race":"White","race_includes_hispanic":false,"race_and_ethnicity":"White (Non-Hispanic)","ingestion_ts":1662607150977}
,{"county_fips":"02122","county_name":"Kenai Peninsula Borough","race_category_id":"WHITE_NH","jail_per_100k":42.0,"jail_pct_share":68.4,"population_pct_share":82.4,"total_confined_children":null,"race":"White","race_includes_hispanic":false,"race_and_ethnicity":"White (Non-Hispanic)","ingestion_ts":1662607150977}
,{"county_fips":"02020","county_name":"Anchorage Municipality","race_category_id":"WHITE_NH","jail_per_100k":null,"jail_pct_share":null,"population_pct_share":61.7,"total_confined_children":null,"race":"White","race_includes_hispanic":false,"race_and_ethnicity":"White (Non-Hispanic)","ingestion_ts":1662607150977}
,{"county_fips":"02130","county_name":"Ketchikan Gateway Borough","race_category_id":"WHITE_NH","jail_per_100k":null,"jail_pct_share":null,"population_pct_share":67.4,"total_confined_children":null,"race":"White","race_includes_hispanic":false,"race_and_ethnicity":"White (Non-Hispanic)","ingestion_ts":1662607150977}
,{"county_fips":"02230","county_name":"Skagway Municipality","race_category_id":"WHITE_NH","jail_per_100k":null,"jail_pct_share":null,"population_pct_share":83.9,"total_confined_children":null,"race":"White","race_includes_hispanic":false,"race_and_ethnicity":"White (Non-Hispanic)","ingestion_ts":1662607150977}
,{"county_fips":"02185","county_name":"North Slope Borough","race_category_id":"WHITE_NH","jail_per_100k":null,"jail_pct_share":null,"population_pct_share":41.1,"total_confined_children":null,"race":"White","race_includes_hispanic":false,"race_and_ethnicity":"White (Non-Hispanic)","ingestion_ts":1662607150977}
,{"county_fips":"02158","county_name":"Kusilvak Census Area","race_category_id":"WHITE_NH","jail_per_100k":null,"jail_pct_share":null,"population_pct_share":4.7,"total_confined_children":null,"race":"White","race_includes_hispanic":false,"race_and_ethnicity":"White (Non-Hispanic)","ingestion_ts":1662607150977}
,{"county_fips":"02068","county_name":"Denali Borough","race_category_id":"WHITE_NH","jail_per_100k":null,"jail_pct_share":null,"population_pct_share":83.2,"total_confined_children":null,"race":"White","race_includes_hispanic":false,"race_and_ethnicity":"White (Non-Hispanic)","ingestion_ts":1662607150977}]
