[{"county_fips":"23005","county_name":"Cumberland County","age":"All","prison_per_100k":200.0,"prison_pct_share":100.0,"population_pct_share":100.0,"total_confined_children":0.0,"ingestion_ts":1662607198533}
,{"county_fips":"23017","county_name":"Oxford County","age":"All","prison_per_100k":193.0,"prison_pct_share":100.0,"population_pct_share":100.0,"total_confined_children":0.0,"ingestion_ts":1662607198533}
,{"county_fips":"23015","county_name":"Lincoln County","age":"All","prison_per_100k":291.0,"prison_pct_share":100.0,"population_pct_share":100.0,"total_confined_children":0.0,"ingestion_ts":1662607198533}
,{"county_fips":"23009","county_name":"Hancock County","age":"All","prison_per_100k":194.0,"prison_pct_share":100.0,"population_pct_share":100.0,"total_confined_children":0.0,"ingestion_ts":1662607198533}
,{"county_fips":"23003","county_name":"Aroostook County","age":"All","prison_per_100k":372.0,"prison_pct_share":100.0,"population_pct_share":100.0,"total_confined_children":0.0,"ingestion_ts":1662607198533}
,{"county_fips":"23023","county_name":"Sagadahoc County","age":"All","prison_per_100k":279.0,"prison_pct_share":100.0,"population_pct_share":100.0,"total_confined_children":0.0,"ingestion_ts":1662607198533}
,{"county_fips":"23001","county_name":"Androscoggin County","age":"All","prison_per_100k":359.0,"prison_pct_share":100.0,"population_pct_share":100.0,"total_confined_children":0.0,"ingestion_ts":1662607198533}
,{"county_fips":"23027","county_name":"Waldo County","age":"All","prison_per_100k":188.0,"prison_pct_share":100.0,"population_pct_share":100.0,"total_confined_children":0.0,"ingestion_ts":1662607198533}
,{"county_fips":"23025","county_name":"Somerset County","age":"All","prison_per_100k":328.0,"prison_pct_share":100.0,"population_pct_share":100.0,"total_confined_children":0.0,"ingestion_ts":1662607198533}
,{"county_fips":"23011","county_name":"Kennebec County","age":"All","prison_per_100k":395.0,"prison_pct_share":100.0,"population_pct_share":100.0,"total_confined_children":0.0,"ingestion_ts":1662607198533}
,{"county_fips":"23007","county_name":"Franklin County","age":"All","prison_per_100k":238.0,"prison_pct_share":100.0,"population_pct_share":100.0,"total_confined_children":0.0,"ingestion_ts":1662607198533}
,{"county_fips":"23013","county_name":"Knox County","age":"All","prison_per_100k":364.0,"prison_pct_share":100.0,"population_pct_share":100.0,"total_confined_children":0.0,"ingestion_ts":1662607198533}
,{"county_fips":"23031","county_name":"York County","age":"All","prison_per_100k":183.0,"prison_pct_share":100.0,"population_pct_share":100.0,"total_confined_children":0.0,"ingestion_ts":1662607198533}
,{"county_fips":"23021","county_name":"Piscataquis County","age":"All","prison_per_100k":223.0,"prison_pct_share":100.0,"population_pct_share":100.0,"total_confined_children":0.0,"ingestion_ts":1662607198533}
,{"county_fips":"23029","county_name":"Washington County","age":"All","prison_per_100k":239.0,"prison_pct_share":100.0,"population_pct_share":100.0,"total_confined_children":0.0,"ingestion_ts":1662607198533}
,{"county_fips":"23019","county_name":"Penobscot County","age":"All","prison_per_100k":350.0,"prison_pct_share":100.0,"population_pct_share":100.0,"total_confined_children":0.0,"ingestion_ts":1662607198533}]
